{
	"info": {
		"_postman_id": "f8ad4536-b932-487e-b1de-830ee2ed2586",
		"name": "blog-posts-platform-backend",
		"description": "# 🚀 Get started here\n\nThis template guides you through CRUD operations (GET, POST, PUT, DELETE), variables, and tests.\n\n## 🔖 **How to use this template**\n\n#### **Step 1: Send requests**\n\nRESTful APIs allow you to perform CRUD operations using the POST, GET, PUT, and DELETE HTTP methods.\n\nThis collection contains each of these [request](https://learning.postman.com/docs/sending-requests/requests/) types. Open each request and click \"Send\" to see what happens.\n\n#### **Step 2: View responses**\n\nObserve the response tab for status code (200 OK), response time, and size.\n\n#### **Step 3: Send new Body data**\n\nUpdate or add new data in \"Body\" in the POST request. Typically, Body data is also used in PUT request.\n\n```\n{\n    \"name\": \"Add your name in the body\"\n}\n\n ```\n\n#### **Step 4: Update the variable**\n\nVariables enable you to store and reuse values in Postman. We have created a [variable](https://learning.postman.com/docs/sending-requests/variables/) called `base_url` with the sample request [https://postman-api-learner.glitch.me](https://postman-api-learner.glitch.me). Replace it with your API endpoint to customize this collection.\n\n#### **Step 5: Add tests in the \"Tests\" tab**\n\nTests help you confirm that your API is working as expected. You can write test scripts in JavaScript and view the output in the \"Test Results\" tab.\n\n<img src=\"https://content.pstmn.io/b5f280a7-4b09-48ec-857f-0a7ed99d7ef8/U2NyZWVuc2hvdCAyMDIzLTAzLTI3IGF0IDkuNDcuMjggUE0ucG5n\">\n\n## 💪 Pro tips\n\n- Use folders to group related requests and organize the collection.\n- Add more [scripts](https://learning.postman.com/docs/writing-scripts/intro-to-scripts/) in \"Tests\" to verify if the API works as expected and execute workflows.\n    \n\n## 💡Related templates\n\n[API testing basics](https://go.postman.co/redirect/workspace?type=personal&collectionTemplateId=e9a37a28-055b-49cd-8c7e-97494a21eb54&sourceTemplateId=ddb19591-3097-41cf-82af-c84273e56719)  \n[API documentation](https://go.postman.co/redirect/workspace?type=personal&collectionTemplateId=e9c28f47-1253-44af-a2f3-20dce4da1f18&sourceTemplateId=ddb19591-3097-41cf-82af-c84273e56719)  \n[Authorization methods](https://go.postman.co/redirect/workspace?type=personal&collectionTemplateId=31a9a6ed-4cdf-4ced-984c-d12c9aec1c27&sourceTemplateId=ddb19591-3097-41cf-82af-c84273e56719)",
		"schema": "https://schema.getpostman.com/json/collection/v2.1.0/collection.json",
		"_exporter_id": "24361999"
	},
	"item": [
		{
			"name": "posts",
			"item": [
				{
					"name": "getPosts",
					"event": [
						{
							"listen": "test",
							"script": {
								"exec": [
									"pm.test(\"Status code is 200\", function () {",
									"    pm.response.to.have.status(200);",
									"});"
								],
								"type": "text/javascript",
								"packages": {}
							}
						}
					],
					"request": {
						"auth": {
							"type": "bearer",
							"bearer": [
								{
									"key": "token",
									"value": "{{JWT}}",
									"type": "string"
								}
							]
						},
						"method": "GET",
						"header": [],
						"url": {
							"raw": "{{LOCAL_HOST}}posts/",
							"host": [
								"{{LOCAL_HOST}}posts"
							],
							"path": [
								""
							],
							"query": [
								{
									"key": "pageNumber",
									"value": "2",
									"disabled": true
								},
								{
									"key": "pageSize",
									"value": "8",
									"disabled": true
								}
							]
						},
						"description": "This is a GET request and it is used to \"get\" data from an endpoint. There is no request body for a GET request, but you can use query parameters to help specify the resource you want data on (e.g., in this request, we have `id=1`).\n\nA successful GET response will have a `200 OK` status, and should include some kind of response body - for example, HTML web content or JSON data."
					},
					"response": []
				},
				{
					"name": "getByIdPost",
					"event": [
						{
							"listen": "test",
							"script": {
								"exec": [
									"pm.test(\"Status code is 200\", function () {",
									"    pm.response.to.have.status(200);",
									"});"
								],
								"type": "text/javascript",
								"packages": {}
							}
						}
					],
					"request": {
						"auth": {
							"type": "bearer",
							"bearer": [
								{
									"key": "token",
									"value": "{{JWT}}",
									"type": "string"
								}
							]
						},
						"method": "GET",
						"header": [],
						"url": {
							"raw": "{{LOCAL_HOST}}posts/6685b19d575ba26453fb4400",
							"host": [
								"{{LOCAL_HOST}}posts"
							],
							"path": [
								"6685b19d575ba26453fb4400"
							]
						},
						"description": "This is a GET request and it is used to \"get\" data from an endpoint. There is no request body for a GET request, but you can use query parameters to help specify the resource you want data on (e.g., in this request, we have `id=1`).\n\nA successful GET response will have a `200 OK` status, and should include some kind of response body - for example, HTML web content or JSON data."
					},
					"response": []
				},
				{
					"name": "deleteByIdPost",
					"event": [
						{
							"listen": "test",
							"script": {
								"exec": [
									"pm.test(\"Status code is 200\", function () {",
									"    pm.response.to.have.status(200);",
									"});"
								],
								"type": "text/javascript",
								"packages": {}
							}
						}
					],
					"request": {
						"auth": {
							"type": "basic",
							"basic": [
								{
									"key": "password",
									"value": "qwerty",
									"type": "string"
								},
								{
									"key": "username",
									"value": "admin",
									"type": "string"
								}
							]
						},
						"method": "DELETE",
						"header": [],
						"url": {
							"raw": "{{LOCAL_HOST}}posts/661b318fa7d6375c786c455b",
							"host": [
								"{{LOCAL_HOST}}posts"
							],
							"path": [
								"661b318fa7d6375c786c455b"
							]
						},
						"description": "This is a GET request and it is used to \"get\" data from an endpoint. There is no request body for a GET request, but you can use query parameters to help specify the resource you want data on (e.g., in this request, we have `id=1`).\n\nA successful GET response will have a `200 OK` status, and should include some kind of response body - for example, HTML web content or JSON data."
					},
					"response": []
				},
				{
					"name": "createPost",
					"event": [
						{
							"listen": "test",
							"script": {
								"exec": [
									"pm.test(\"Status code is 200\", function () {",
									"    pm.response.to.have.status(200);",
									"});"
								],
								"type": "text/javascript",
								"packages": {}
							}
						}
					],
					"request": {
						"auth": {
							"type": "basic",
							"basic": [
								{
									"key": "password",
									"value": "qwerty",
									"type": "string"
								},
								{
									"key": "username",
									"value": "admin",
									"type": "string"
								}
							]
						},
						"method": "POST",
						"header": [],
						"body": {
							"mode": "raw",
							"raw": "{\r\n    \"title\": \"Is memo still needs?\",\r\n    \"shortDescription\": \"short description for post\",\r\n    \"content\": \"content is comming up soon\",\r\n    \"blogId\": \"662bf8758f1a93a2082eb4ee\"\r\n}",
							"options": {
								"raw": {
									"language": "json"
								}
							}
						},
						"url": {
							"raw": "{{LOCAL_HOST}}posts/",
							"host": [
								"{{LOCAL_HOST}}posts"
							],
							"path": [
								""
							]
						},
						"description": "This is a GET request and it is used to \"get\" data from an endpoint. There is no request body for a GET request, but you can use query parameters to help specify the resource you want data on (e.g., in this request, we have `id=1`).\n\nA successful GET response will have a `200 OK` status, and should include some kind of response body - for example, HTML web content or JSON data."
					},
					"response": []
				},
				{
					"name": "updatePost",
					"event": [
						{
							"listen": "test",
							"script": {
								"exec": [
									"pm.test(\"Status code is 200\", function () {",
									"    pm.response.to.have.status(200);",
									"});"
								],
								"type": "text/javascript",
								"packages": {}
							}
						}
					],
					"request": {
						"auth": {
							"type": "basic",
							"basic": [
								{
									"key": "password",
									"value": "qwerty",
									"type": "string"
								},
								{
									"key": "username",
									"value": "admin",
									"type": "string"
								}
							]
						},
						"method": "PUT",
						"header": [],
						"body": {
							"mode": "raw",
							"raw": "{\r\n  \"title\": \"What is REST API's?\",\r\n      \"shortDescription\": \"short description for post\",\r\n    \"content\": \"content is comming up soon\",\r\n  \"blogId\": \"665de0b0ed6b88ba049eae66\"\r\n}",
							"options": {
								"raw": {
									"language": "json"
								}
							}
						},
						"url": {
							"raw": "{{LOCAL_HOST}}posts/665de57830b3232b4da8dfb1",
							"host": [
								"{{LOCAL_HOST}}posts"
							],
							"path": [
								"665de57830b3232b4da8dfb1"
							]
						},
						"description": "This is a GET request and it is used to \"get\" data from an endpoint. There is no request body for a GET request, but you can use query parameters to help specify the resource you want data on (e.g., in this request, we have `id=1`).\n\nA successful GET response will have a `200 OK` status, and should include some kind of response body - for example, HTML web content or JSON data."
					},
					"response": []
				},
				{
					"name": "createComment",
					"request": {
						"auth": {
							"type": "bearer",
							"bearer": [
								{
									"key": "token",
									"value": "{{JWT}}",
									"type": "string"
								}
							]
						},
						"method": "POST",
						"header": [],
						"body": {
							"mode": "raw",
							"raw": "{\r\n    \"content\": \"Final touch up of likes logic2\"\r\n}",
							"options": {
								"raw": {
									"language": "json"
								}
							}
						},
						"url": {
							"raw": "{{LOCAL_HOST}}posts/6685b19d575ba26453fb4400/comments",
							"host": [
								"{{LOCAL_HOST}}posts"
							],
							"path": [
								"6685b19d575ba26453fb4400",
								"comments"
							]
						}
					},
					"response": []
				},
				{
					"name": "reactToPost",
					"request": {
						"auth": {
							"type": "bearer",
							"bearer": [
								{
									"key": "token",
									"value": "{{JWT}}",
									"type": "string"
								}
							]
						},
						"method": "PUT",
						"header": [],
						"body": {
							"mode": "raw",
							"raw": "{\r\n    \"likeStatus\": \"Like\"\r\n}",
							"options": {
								"raw": {
									"language": "json"
								}
							}
						},
						"url": {
							"raw": "{{LOCAL_HOST}}comments/668302cbc326fa47497d7cbc/like-status",
							"host": [
								"{{LOCAL_HOST}}comments"
							],
							"path": [
								"668302cbc326fa47497d7cbc",
								"like-status"
							]
						}
					},
					"response": []
				},
				{
					"name": "getPostComments",
					"request": {
						"auth": {
							"type": "bearer",
							"bearer": [
								{
									"key": "token",
									"value": "{{JWT}}",
									"type": "string"
								}
							]
						},
						"method": "GET",
						"header": [],
						"url": {
							"raw": "{{LOCAL_HOST}}posts/6685b19d575ba26453fb4400/comments",
							"host": [
								"{{LOCAL_HOST}}posts"
							],
							"path": [
								"6685b19d575ba26453fb4400",
								"comments"
							]
						}
					},
					"response": []
				}
			]
		},
		{
			"name": "blogs",
			"item": [
				{
					"name": "getBlogs",
					"event": [
						{
							"listen": "test",
							"script": {
								"exec": [
									"pm.test(\"Status code is 200\", function () {",
									"    pm.response.to.have.status(200);",
									"});"
								],
								"type": "text/javascript",
								"packages": {}
							}
						}
					],
					"request": {
						"method": "GET",
						"header": [],
						"url": {
							"raw": "{{LOCAL_HOST}}blogs/",
							"host": [
								"{{LOCAL_HOST}}blogs"
							],
							"path": [
								""
							],
							"query": [
								{
									"key": "searchNameTerm",
									"value": "new blog9",
									"disabled": true
								},
								{
									"key": "pageNumber",
									"value": "2",
									"disabled": true
								},
								{
									"key": "pageSize",
									"value": "2",
									"disabled": true
								}
							]
						},
						"description": "This is a GET request and it is used to \"get\" data from an endpoint. There is no request body for a GET request, but you can use query parameters to help specify the resource you want data on (e.g., in this request, we have `id=1`).\n\nA successful GET response will have a `200 OK` status, and should include some kind of response body - for example, HTML web content or JSON data."
					},
					"response": []
				},
				{
					"name": "getByIdBlog",
					"event": [
						{
							"listen": "test",
							"script": {
								"exec": [
									"pm.test(\"Status code is 200\", function () {",
									"    pm.response.to.have.status(200);",
									"});"
								],
								"type": "text/javascript",
								"packages": {}
							}
						}
					],
					"request": {
						"method": "GET",
						"header": [],
						"url": {
							"raw": "{{LOCAL_HOST}}blogs/665de0b0ed6b88ba049eae66",
							"host": [
								"{{LOCAL_HOST}}blogs"
							],
							"path": [
								"665de0b0ed6b88ba049eae66"
							]
						},
						"description": "This is a GET request and it is used to \"get\" data from an endpoint. There is no request body for a GET request, but you can use query parameters to help specify the resource you want data on (e.g., in this request, we have `id=1`).\n\nA successful GET response will have a `200 OK` status, and should include some kind of response body - for example, HTML web content or JSON data."
					},
					"response": []
				},
				{
					"name": "getBlogPosts",
					"event": [
						{
							"listen": "test",
							"script": {
								"exec": [
									"pm.test(\"Status code is 200\", function () {",
									"    pm.response.to.have.status(200);",
									"});"
								],
								"type": "text/javascript",
								"packages": {}
							}
						}
					],
					"request": {
						"auth": {
							"type": "noauth"
						},
						"method": "GET",
						"header": [],
						"url": {
							"raw": "{{LOCAL_HOST}}blogs/6622ef7c21929e7cd3bea314/posts",
							"host": [
								"{{LOCAL_HOST}}blogs"
							],
							"path": [
								"6622ef7c21929e7cd3bea314",
								"posts"
							],
							"query": [
								{
									"key": "pageSize",
									"value": "3",
									"disabled": true
								},
								{
									"key": "pageNumber",
									"value": "2",
									"disabled": true
								}
							]
						},
						"description": "This is a GET request and it is used to \"get\" data from an endpoint. There is no request body for a GET request, but you can use query parameters to help specify the resource you want data on (e.g., in this request, we have `id=1`).\n\nA successful GET response will have a `200 OK` status, and should include some kind of response body - for example, HTML web content or JSON data."
					},
					"response": []
				},
				{
					"name": "deleteByIdBlog",
					"event": [
						{
							"listen": "test",
							"script": {
								"exec": [
									"pm.test(\"Status code is 200\", function () {",
									"    pm.response.to.have.status(200);",
									"});"
								],
								"type": "text/javascript",
								"packages": {}
							}
						}
					],
					"request": {
						"auth": {
							"type": "basic",
							"basic": [
								{
									"key": "password",
									"value": "qwerty",
									"type": "string"
								},
								{
									"key": "username",
									"value": "admin",
									"type": "string"
								}
							]
						},
						"method": "DELETE",
						"header": [],
						"url": {
							"raw": "{{LOCAL_HOST}}blogs/665dddae800487a63830d421",
							"host": [
								"{{LOCAL_HOST}}blogs"
							],
							"path": [
								"665dddae800487a63830d421"
							]
						},
						"description": "This is a GET request and it is used to \"get\" data from an endpoint. There is no request body for a GET request, but you can use query parameters to help specify the resource you want data on (e.g., in this request, we have `id=1`).\n\nA successful GET response will have a `200 OK` status, and should include some kind of response body - for example, HTML web content or JSON data."
					},
					"response": []
				},
				{
					"name": "createBlog",
					"event": [
						{
							"listen": "test",
							"script": {
								"exec": [
									"pm.test(\"Status code is 201\", function () {",
									"    pm.response.to.have.status(201);",
									"});"
								],
								"type": "text/javascript",
								"packages": {}
							}
						}
					],
					"request": {
						"auth": {
							"type": "basic",
							"basic": [
								{
									"key": "password",
									"value": "qwerty",
									"type": "string"
								},
								{
									"key": "username",
									"value": "admin",
									"type": "string"
								}
							]
						},
						"method": "POST",
						"header": [],
						"body": {
							"mode": "raw",
							"raw": "{\r\n    \"name\": \"REST APIs\",\r\n    \"description\": \"here is short description for blog of REST API's\",\r\n    \"websiteUrl\": \"https://www.geeksforgeeks.org/what-to-understand-callback-and-callback-hell-in-javascript/\"\r\n}",
							"options": {
								"raw": {
									"language": "json"
								}
							}
						},
						"url": {
							"raw": "{{LOCAL_HOST}}blogs/",
							"host": [
								"{{LOCAL_HOST}}blogs"
							],
							"path": [
								""
							]
						},
						"description": "This is a GET request and it is used to \"get\" data from an endpoint. There is no request body for a GET request, but you can use query parameters to help specify the resource you want data on (e.g., in this request, we have `id=1`).\n\nA successful GET response will have a `200 OK` status, and should include some kind of response body - for example, HTML web content or JSON data."
					},
					"response": []
				},
				{
					"name": "createBlogPost",
					"event": [
						{
							"listen": "test",
							"script": {
								"exec": [
									"pm.test(\"Status code is 200\", function () {",
									"    pm.response.to.have.status(200);",
									"});"
								],
								"type": "text/javascript",
								"packages": {}
							}
						}
					],
					"request": {
						"auth": {
							"type": "basic",
							"basic": [
								{
									"key": "password",
									"value": "qwerty",
									"type": "string"
								},
								{
									"key": "username",
									"value": "admin",
									"type": "string"
								}
							]
						},
						"method": "POST",
						"header": [],
						"body": {
							"mode": "raw",
							"raw": "{\r\n    \"title\": \"What is callback\",\r\n    \"shortDescription\": \"description for memo post\",\r\n    \"content\": \"content is comming\"\r\n}",
							"options": {
								"raw": {
									"language": "json"
								}
							}
						},
						"url": {
							"raw": "{{LOCAL_HOST}}blogs/6622ef7c21929e7cd3bea314/posts",
							"host": [
								"{{LOCAL_HOST}}blogs"
							],
							"path": [
								"6622ef7c21929e7cd3bea314",
								"posts"
							]
						},
						"description": "This is a GET request and it is used to \"get\" data from an endpoint. There is no request body for a GET request, but you can use query parameters to help specify the resource you want data on (e.g., in this request, we have `id=1`).\n\nA successful GET response will have a `200 OK` status, and should include some kind of response body - for example, HTML web content or JSON data."
					},
					"response": []
				},
				{
					"name": "updateBlog",
					"event": [
						{
							"listen": "test",
							"script": {
								"exec": [
									"pm.test(\"Status code is 200\", function () {",
									"    pm.response.to.have.status(200);",
									"});"
								],
								"type": "text/javascript",
								"packages": {}
							}
						}
					],
					"request": {
						"auth": {
							"type": "basic",
							"basic": [
								{
									"key": "password",
									"value": "qwerty",
									"type": "string"
								},
								{
									"key": "username",
									"value": "admin",
									"type": "string"
								}
							]
						},
						"method": "PUT",
						"header": [],
						"body": {
							"mode": "raw",
							"raw": "{\r\n    \"name\": \"memo\",\r\n    \"description\": \"new memo\",\r\n    \"websiteUrl\": \"https://www.google.com\"\r\n}",
							"options": {
								"raw": {
									"language": "json"
								}
							}
						},
						"url": {
							"raw": "{{LOCAL_HOST}}blogs/661d6a7ef996cd1033ea2933",
							"host": [
								"{{LOCAL_HOST}}blogs"
							],
							"path": [
								"661d6a7ef996cd1033ea2933"
							]
						},
						"description": "This is a GET request and it is used to \"get\" data from an endpoint. There is no request body for a GET request, but you can use query parameters to help specify the resource you want data on (e.g., in this request, we have `id=1`).\n\nA successful GET response will have a `200 OK` status, and should include some kind of response body - for example, HTML web content or JSON data."
					},
					"response": []
				}
			]
		},
		{
			"name": "TEST",
			"item": [
				{
					"name": "RemoveAllData",
					"request": {
						"method": "DELETE",
						"header": [],
						"url": {
							"raw": "{{LOCAL_HOST}}all-data/",
							"host": [
								"{{LOCAL_HOST}}all-data"
							],
							"path": [
								""
							]
						}
					},
					"response": []
				}
			]
		},
		{
			"name": "users",
			"item": [
				{
					"name": "deleteByIdUser",
					"event": [
						{
							"listen": "test",
							"script": {
								"exec": [
									"pm.test(\"Status code is 200\", function () {",
									"    pm.response.to.have.status(200);",
									"});"
								],
								"type": "text/javascript",
								"packages": {}
							}
						}
					],
					"request": {
						"auth": {
							"type": "basic",
							"basic": [
								{
									"key": "password",
									"value": "qwerty",
									"type": "string"
								},
								{
									"key": "username",
									"value": "admin",
									"type": "string"
								}
							]
						},
						"method": "DELETE",
						"header": [],
						"url": {
							"raw": "{{LOCAL_HOST}}users/6625d7eeceac820bdc07b6e1",
							"host": [
								"{{LOCAL_HOST}}users"
							],
							"path": [
								"6625d7eeceac820bdc07b6e1"
							]
						},
						"description": "This is a GET request and it is used to \"get\" data from an endpoint. There is no request body for a GET request, but you can use query parameters to help specify the resource you want data on (e.g., in this request, we have `id=1`).\n\nA successful GET response will have a `200 OK` status, and should include some kind of response body - for example, HTML web content or JSON data."
					},
					"response": []
				},
				{
					"name": "createUser",
					"event": [
						{
							"listen": "test",
							"script": {
								"exec": [
									"pm.test(\"Status code is 200\", function () {",
									"    pm.response.to.have.status(200);",
									"});"
								],
								"type": "text/javascript",
								"packages": {}
							}
						}
					],
					"request": {
						"auth": {
							"type": "basic",
							"basic": [
								{
									"key": "password",
									"value": "qwerty",
									"type": "string"
								},
								{
									"key": "username",
									"value": "admin",
									"type": "string"
								}
							]
						},
						"method": "POST",
						"header": [],
						"body": {
							"mode": "raw",
							"raw": "{\r\n  \"login\": \"oksanaYo\",\r\n  \"password\": \"string12\",\r\n  \"email\": \"oprokopieva382@gmail.com\"\r\n}",
							"options": {
								"raw": {
									"language": "json"
								}
							}
						},
						"url": {
							"raw": "{{LOCAL_HOST}}users/",
							"host": [
								"{{LOCAL_HOST}}users"
							],
							"path": [
								""
							]
						},
						"description": "This is a GET request and it is used to \"get\" data from an endpoint. There is no request body for a GET request, but you can use query parameters to help specify the resource you want data on (e.g., in this request, we have `id=1`).\n\nA successful GET response will have a `200 OK` status, and should include some kind of response body - for example, HTML web content or JSON data."
					},
					"response": []
				},
				{
					"name": "getUsers",
					"request": {
						"auth": {
							"type": "basic",
							"basic": [
								{
									"key": "password",
									"value": "qwerty",
									"type": "string"
								},
								{
									"key": "username",
									"value": "admin",
									"type": "string"
								}
							]
						},
						"method": "GET",
						"header": [],
						"url": {
							"raw": "{{LOCAL_HOST}}users/",
							"host": [
								"{{LOCAL_HOST}}users"
							],
							"path": [
								""
							]
						}
					},
					"response": []
				},
				{
					"name": "getByIdUser",
					"request": {
						"auth": {
							"type": "basic",
							"basic": [
								{
									"key": "password",
									"value": "qwerty",
									"type": "string"
								},
								{
									"key": "username",
									"value": "admin",
									"type": "string"
								}
							]
						},
						"method": "GET",
						"header": [],
						"url": {
							"raw": "{{LOCAL_HOST}}users/",
							"host": [
								"{{LOCAL_HOST}}users"
							],
							"path": [
								""
							]
						}
					},
					"response": []
				}
			]
		},
		{
			"name": "auth",
			"item": [
				{
					"name": "authLogin",
					"event": [
						{
							"listen": "test",
							"script": {
								"exec": [
									"var jsonData = pm.response.json();\r",
									"pm.environment.set(\"JWT\", jsonData.accessToken);"
								],
								"type": "text/javascript",
								"packages": {}
							}
						}
					],
					"request": {
						"method": "POST",
						"header": [],
						"body": {
							"mode": "raw",
							"raw": "{\r\n     \"loginOrEmail\": \"oksanaYo\",\r\n     \"password\": \"string12\"\r\n}",
							"options": {
								"raw": {
									"language": "json"
								}
							}
						},
						"url": {
							"raw": "{{LOCAL_HOST}}auth/login",
							"host": [
								"{{LOCAL_HOST}}auth"
							],
							"path": [
								"login"
							]
						}
					},
					"response": []
				},
				{
					"name": "authRefreshToken",
					"event": [
						{
							"listen": "test",
							"script": {
								"exec": [
									"var jsonData = pm.response.json();\r",
									"pm.environment.set(\"JWT\", jsonData.accessToken);"
								],
								"type": "text/javascript",
								"packages": {}
							}
						}
					],
					"request": {
						"method": "POST",
						"header": [],
						"body": {
							"mode": "raw",
							"raw": "",
							"options": {
								"raw": {
									"language": "json"
								}
							}
						},
						"url": {
							"raw": "{{LOCAL_HOST}}auth/refresh-token",
							"host": [
								"{{LOCAL_HOST}}auth"
							],
							"path": [
								"refresh-token"
							]
						}
					},
					"response": []
				},
				{
					"name": "authLogout",
					"event": [
						{
							"listen": "test",
							"script": {
								"exec": [
									""
								],
								"type": "text/javascript",
								"packages": {}
							}
						}
					],
					"request": {
						"method": "POST",
						"header": [],
						"body": {
							"mode": "raw",
							"raw": "",
							"options": {
								"raw": {
									"language": "json"
								}
							}
						},
						"url": {
							"raw": "{{LOCAL_HOST}}auth/logout",
							"host": [
								"{{LOCAL_HOST}}auth"
							],
							"path": [
								"logout"
							]
						}
					},
					"response": []
				},
				{
					"name": "registration",
					"request": {
						"method": "POST",
						"header": [],
						"body": {
							"mode": "raw",
							"raw": "{\r\n  \"login\": \"OksanaYo\",\r\n  \"password\": \"oksana12\",\r\n  \"email\": \"oprokopieva382@gmail.com\"\r\n}",
							"options": {
								"raw": {
									"language": "json"
								}
							}
						},
						"url": {
							"raw": "{{LOCAL_HOST}}auth/registration",
							"host": [
								"{{LOCAL_HOST}}auth"
							],
							"path": [
								"registration"
							]
						}
					},
					"response": []
				},
				{
					"name": "registrationResending",
					"request": {
						"method": "POST",
						"header": [],
						"body": {
							"mode": "raw",
							"raw": "{\r\n  \"login\": \"OksanaYo\",\r\n  \"password\": \"oksana1234\",\r\n  \"email\": \"oprokopieva382@gmail.com\"\r\n}",
							"options": {
								"raw": {
									"language": "json"
								}
							}
						},
						"url": {
							"raw": "{{LOCAL_HOST}}auth/registration",
							"host": [
								"{{LOCAL_HOST}}auth"
							],
							"path": [
								"registration"
							]
						}
					},
					"response": []
				},
				{
					"name": "registrationConfirmation",
					"request": {
						"method": "POST",
						"header": [],
						"body": {
							"mode": "raw",
							"raw": "{\r\n     \"code\": \"f7eadde9-6116-4f14-92b0-817b1fdb36eb\"\r\n  }",
							"options": {
								"raw": {
									"language": "json"
								}
							}
						},
						"url": {
							"raw": "{{LOCAL_HOST}}auth/registration-confirmation",
							"host": [
								"{{LOCAL_HOST}}auth"
							],
							"path": [
								"registration-confirmation"
							]
						}
					},
					"response": []
				},
				{
					"name": "authMe",
					"request": {
						"auth": {
							"type": "bearer",
							"bearer": [
								{
									"key": "token",
									"value": "{{JWT}}",
									"type": "string"
								}
							]
						},
						"method": "GET",
						"header": [],
						"url": {
							"raw": "{{LOCAL_HOST}}auth/me",
							"host": [
								"{{LOCAL_HOST}}auth"
							],
							"path": [
								"me"
							]
						}
					},
					"response": []
				},
				{
					"name": "vercel",
					"request": {
						"method": "GET",
						"header": []
					},
					"response": []
				},
				{
					"name": "passwordRecovery",
					"request": {
						"method": "POST",
						"header": [],
						"url": {
							"raw": "{{LOCAL_HOST}}auth/password-recovery",
							"host": [
								"{{LOCAL_HOST}}auth"
							],
							"path": [
								"password-recovery"
							]
						}
					},
					"response": []
				},
				{
					"name": "setNewPassword",
					"request": {
						"method": "POST",
						"header": [],
						"url": {
							"raw": "{{LOCAL_HOST}}auth/password-recovery",
							"host": [
								"{{LOCAL_HOST}}auth"
							],
							"path": [
								"password-recovery"
							]
						}
					},
					"response": []
				}
			]
		},
		{
			"name": "comments",
			"item": [
				{
					"name": "getByIdComment",
					"request": {
						"auth": {
							"type": "bearer",
							"bearer": [
								{
									"key": "token",
									"value": "{{JWT}}",
									"type": "string"
								}
							]
						},
						"method": "GET",
						"header": [],
						"url": {
							"raw": "{{LOCAL_HOST}}comments/6685d9f2eae62f6626a77936",
							"host": [
								"{{LOCAL_HOST}}comments"
							],
							"path": [
								"6685d9f2eae62f6626a77936"
							]
						}
					},
					"response": []
				},
				{
					"name": "updateComment",
					"request": {
						"auth": {
							"type": "bearer",
							"bearer": [
								{
									"key": "token",
									"value": "{{JWT}}",
									"type": "string"
								}
							]
						},
						"method": "PUT",
						"header": [],
						"body": {
							"mode": "raw",
							"raw": "{\r\n    \"content\": \"It is such a great content\"\r\n}",
							"options": {
								"raw": {
									"language": "json"
								}
							}
						},
						"url": {
							"raw": "{{LOCAL_HOST}}comments/662c44d79f88e7263a531f61",
							"host": [
								"{{LOCAL_HOST}}comments"
							],
							"path": [
								"662c44d79f88e7263a531f61"
							]
						}
					},
					"response": []
				},
				{
					"name": "reactToComment",
					"request": {
						"auth": {
							"type": "bearer",
							"bearer": [
								{
									"key": "token",
									"value": "{{JWT}}",
									"type": "string"
								}
							]
						},
						"method": "PUT",
						"header": [],
						"body": {
							"mode": "raw",
							"raw": "{\r\n    \"likeStatus\": \"Like\"\r\n}",
							"options": {
								"raw": {
									"language": "json"
								}
							}
						},
						"url": {
							"raw": "{{LOCAL_HOST}}comments/668302cbc326fa47497d7cbc/like-status",
							"host": [
								"{{LOCAL_HOST}}comments"
							],
							"path": [
								"668302cbc326fa47497d7cbc",
								"like-status"
							]
						}
					},
					"response": []
				},
				{
					"name": "deleteComment",
					"request": {
						"auth": {
							"type": "bearer",
							"bearer": [
								{
									"key": "token",
									"value": "{{JWT}}",
									"type": "string"
								}
							]
						},
						"method": "DELETE",
						"header": [],
						"url": {
							"raw": "{{LOCAL_HOST}}comments/662c44d79f88e7263a531f61",
							"host": [
								"{{LOCAL_HOST}}comments"
							],
							"path": [
								"662c44d79f88e7263a531f61"
							]
						}
					},
					"response": []
				}
			]
		},
		{
			"name": "sessions",
			"item": [
				{
					"name": "getAll",
					"event": [
						{
							"listen": "test",
							"script": {
								"exec": [
									""
								],
								"type": "text/javascript",
								"packages": {}
							}
						}
					],
					"protocolProfileBehavior": {
						"disabledSystemHeaders": {}
					},
					"request": {
						"auth": {
							"type": "bearer",
							"bearer": [
								{
									"key": "token",
									"value": "{{JWT}}",
									"type": "string"
								}
							]
						},
						"method": "GET",
						"header": [],
						"url": {
							"raw": "{{LOCAL_HOST}}security/devices",
							"host": [
								"{{LOCAL_HOST}}security"
							],
							"path": [
								"devices"
							]
						}
					},
					"response": []
				},
				{
					"name": "deleteByDeviceId",
					"event": [
						{
							"listen": "test",
							"script": {
								"exec": [
									""
								],
								"type": "text/javascript",
								"packages": {}
							}
						}
					],
					"request": {
						"auth": {
							"type": "bearer",
							"bearer": [
								{
									"key": "token",
									"value": "{{JWT}}",
									"type": "string"
								}
							]
						},
						"method": "DELETE",
						"header": [],
						"url": {
							"raw": "{{LOCAL_HOST}}security/devices/b0f78858-f7ac-4654-b2c9-bfbe1eb95b88",
							"host": [
								"{{LOCAL_HOST}}security"
							],
							"path": [
								"devices",
								"b0f78858-f7ac-4654-b2c9-bfbe1eb95b88"
							]
						}
					},
					"response": []
				},
				{
					"name": "deleteAll",
					"event": [
						{
							"listen": "test",
							"script": {
								"exec": [
									""
								],
								"type": "text/javascript",
								"packages": {}
							}
						}
					],
					"request": {
						"auth": {
							"type": "bearer",
							"bearer": [
								{
									"key": "token",
									"value": "{{JWT}}",
									"type": "string"
								}
							]
						},
						"method": "DELETE",
						"header": [],
						"url": {
							"raw": "{{LOCAL_HOST}}security/devices/",
							"host": [
								"{{LOCAL_HOST}}security"
							],
							"path": [
								"devices",
								""
							]
						}
					},
					"response": []
				}
			]
		}
	],
	"event": [
		{
			"listen": "prerequest",
			"script": {
				"type": "text/javascript",
				"exec": [
					""
				]
			}
		},
		{
			"listen": "test",
			"script": {
				"type": "text/javascript",
				"exec": [
					""
				]
			}
		}
	],
	"variable": [
		{
			"key": "id",
			"value": "1"
		},
		{
			"key": "base_url",
			"value": "https://postman-rest-api-learner.glitch.me/"
		}
	]
}